setlr/__init__.py
setlr/core.py
setlr/iterparse_filter.py
setlr/trig_store.py
setlr-1.0.2.dist-info/licenses/LICENSE
setlr-1.0.2.dist-info/METADATA
setlr-1.0.2.dist-info/WHEEL
setlr-1.0.2.dist-info/entry_points.txt
setlr-1.0.2.dist-info/top_level.txt
setlr-1.0.2.dist-info/RECORD
