Metadata-Version: 2.4
Name: setlr
Version: 1.0.2
Summary: setlr is a tool for Semantic Extraction, Transformation, and Loading.
Author-email: Jamie McCusker <mccusj@cs.rpi.edu>
Project-URL: Homepage, http://packages.python.org/setlr
Keywords: rdf,semantic,etl
Classifier: Development Status :: 5 - Production/Stable
Classifier: Topic :: Utilities
Requires-Python: >=3.8
License-File: LICENSE
Requires-Dist: future
Requires-Dist: cython
Requires-Dist: numpy
Requires-Dist: rdflib>=6.0.0
Requires-Dist: pandas>=0.23.0
Requires-Dist: requests
Requires-Dist: toposort
Requires-Dist: beautifulsoup4
Requires-Dist: jinja2
Requires-Dist: lxml
Requires-Dist: six
Requires-Dist: xlrd
Requires-Dist: ijson
Requires-Dist: click
Requires-Dist: tqdm
Requires-Dist: requests-testadapter
Requires-Dist: python-slugify
Requires-Dist: pyshacl[js]
Dynamic: license-file
